nuamo/__init__.py
nuamo/__main__.py
nuamo/char_model.py
nuamo/google_searcher.py
nuamo-0.2.2.dist-info/LICENSE
nuamo-0.2.2.dist-info/METADATA
nuamo-0.2.2.dist-info/WHEEL
nuamo-0.2.2.dist-info/entry_points.txt
nuamo-0.2.2.dist-info/top_level.txt
nuamo-0.2.2.dist-info/RECORD
