Metadata-Version: 2.1
Name: nuamo
Version: 0.2.2
Summary: Tool to generate potential project names
Home-page: https://github.com/MatthewScholefield/nuamo
Author: Matthew Scholefield
Author-email: matthew331199@gmail.com
License: UNKNOWN
Keywords: nuamo project name nlp
Platform: UNKNOWN
Classifier: Development Status :: 3 - Alpha
Classifier: Intended Audience :: Developers
Classifier: Programming Language :: Python :: 3
Classifier: Programming Language :: Python :: 3.5
Classifier: Programming Language :: Python :: 3.6
Classifier: Programming Language :: Python :: 3.7
Requires-Dist: requests
